BioNick/__init__.py
BioNick/functions.py
BioNick/interface.py
BioNick-0.0.7.dist-info/LICENSE
BioNick-0.0.7.dist-info/METADATA
BioNick-0.0.7.dist-info/WHEEL
BioNick-0.0.7.dist-info/top_level.txt
BioNick-0.0.7.dist-info/RECORD
