Metadata-Version: 2.1
Name: BioNick
Version: 0.0.7
Summary: Tools for newick file manipulation and visualization.
Home-page: https://github.com/DeadlineWasYesterday/BioNick
Author: Md Nafis Ul Alam
Author-email: deadlinewasyesterday@gmail.com
Classifier: Intended Audience :: Developers
Classifier: Intended Audience :: Science/Research
Classifier: License :: Freely Distributable
Classifier: Operating System :: OS Independent
Classifier: Programming Language :: Python
Classifier: Programming Language :: Python :: 3.12
Classifier: Topic :: Scientific/Engineering
Classifier: Topic :: Scientific/Engineering :: Bio-Informatics
Requires-Python: >=3.5
License-File: LICENSE
Requires-Dist: numpy
Requires-Dist: pandas
Requires-Dist: matplotlib
